whois/__init__.py
whois/whois.py
pa_whois-0.1.0.dist-info/LICENCE
pa_whois-0.1.0.dist-info/METADATA
pa_whois-0.1.0.dist-info/WHEEL
pa_whois-0.1.0.dist-info/top_level.txt
pa_whois-0.1.0.dist-info/RECORD
