Metadata-Version: 2.1
Name: pa-whois
Version: 0.1.0
Summary: Python wrapper for Prompt API's Whois API
Home-page: https://github.com/promptapi/whois-py
Author: Prompt API
Author-email: hello@promptapi.com
License: MIT
Project-URL: Prompt API, https://promptapi.com
Project-URL: Scraper API, https://promptapi.com/marketplace/description/whois-api
Project-URL: Source, https://github.com/promptapi/whois-py
Keywords: promptapi,whois,domain-name,domain-lookup,api
Platform: UNKNOWN
Classifier: Development Status :: 1 - Planning
Classifier: License :: OSI Approved :: MIT License
Classifier: Operating System :: OS Independent
Classifier: Programming Language :: Python :: 3
Classifier: Programming Language :: Python :: 3.7
Classifier: Programming Language :: Python :: 3 :: Only
Classifier: Intended Audience :: Developers
Classifier: Intended Audience :: Information Technology
Classifier: Topic :: Software Development :: Libraries :: Python Modules
Classifier: Topic :: Internet :: WWW/HTTP
Requires-Python: >=3.7
Requires-Dist: requests
Provides-Extra: development
Requires-Dist: vb-console ; extra == 'development'
